{
  "mainAssemblyName": "theonlytool",
  "resources": {
    "hash": "sha256-8Zvb+EeCoWtKkOOZ3kjbLZxC4uta8sikM7unwksFyiQ=",
    "fingerprinting": {
      "Microsoft.AspNetCore.Components.Forms.3qh9t4or2h.wasm": "Microsoft.AspNetCore.Components.Forms.wasm",
      "Microsoft.AspNetCore.Components.Web.xxzncl2btm.wasm": "Microsoft.AspNetCore.Components.Web.wasm",
      "Microsoft.AspNetCore.Components.WebAssembly.nvr1tj7rwf.wasm": "Microsoft.AspNetCore.Components.WebAssembly.wasm",
      "Microsoft.AspNetCore.Components.1jbluefeqp.wasm": "Microsoft.AspNetCore.Components.wasm",
      "Microsoft.Extensions.Configuration.Abstractions.s1desti5lj.wasm": "Microsoft.Extensions.Configuration.Abstractions.wasm",
      "Microsoft.Extensions.Configuration.Json.6ap0l7oqnx.wasm": "Microsoft.Extensions.Configuration.Json.wasm",
      "Microsoft.Extensions.Configuration.wzhhqnelnl.wasm": "Microsoft.Extensions.Configuration.wasm",
      "Microsoft.Extensions.DependencyInjection.t7f5r90yql.wasm": "Microsoft.Extensions.DependencyInjection.wasm",
      "Microsoft.Extensions.DependencyInjection.Abstractions.k3obqto650.wasm": "Microsoft.Extensions.DependencyInjection.Abstractions.wasm",
      "Microsoft.Extensions.FileProviders.Abstractions.zo7f77cwpb.wasm": "Microsoft.Extensions.FileProviders.Abstractions.wasm",
      "Microsoft.Extensions.Hosting.Abstractions.oq0bc6qwtw.wasm": "Microsoft.Extensions.Hosting.Abstractions.wasm",
      "Microsoft.Extensions.Localization.Abstractions.ixsppbtym0.wasm": "Microsoft.Extensions.Localization.Abstractions.wasm",
      "Microsoft.Extensions.Localization.bvn14pws96.wasm": "Microsoft.Extensions.Localization.wasm",
      "Microsoft.Extensions.Logging.bvp0h3knwz.wasm": "Microsoft.Extensions.Logging.wasm",
      "Microsoft.Extensions.Logging.Abstractions.tx3rk9lhk3.wasm": "Microsoft.Extensions.Logging.Abstractions.wasm",
      "Microsoft.Extensions.Options.7oidopj7m4.wasm": "Microsoft.Extensions.Options.wasm",
      "Microsoft.Extensions.Primitives.a5mjza44y9.wasm": "Microsoft.Extensions.Primitives.wasm",
      "Microsoft.JSInterop.evnp8zttjq.wasm": "Microsoft.JSInterop.wasm",
      "Microsoft.JSInterop.WebAssembly.9tiedlnvko.wasm": "Microsoft.JSInterop.WebAssembly.wasm",
      "MudBlazor.65z43161st.wasm": "MudBlazor.wasm",
      "Services.Base64.8b93i9ca7z.wasm": "Services.Base64.wasm",
      "Services.Hashing.e8mmxusnr1.wasm": "Services.Hashing.wasm",
      "Services.Url.ufhjhi9cut.wasm": "Services.Url.wasm",
      "System.Collections.prf43m75vm.wasm": "System.Collections.wasm",
      "System.Collections.Concurrent.ablm14sie8.wasm": "System.Collections.Concurrent.wasm",
      "System.Collections.Immutable.s4jrvfcbhz.wasm": "System.Collections.Immutable.wasm",
      "System.ComponentModel.Annotations.gruad1a9u6.wasm": "System.ComponentModel.Annotations.wasm",
      "System.ComponentModel.Primitives.ai1jrkm3wb.wasm": "System.ComponentModel.Primitives.wasm",
      "System.ComponentModel.TypeConverter.p0djjcxzit.wasm": "System.ComponentModel.TypeConverter.wasm",
      "System.ComponentModel.fac0tpga5u.wasm": "System.ComponentModel.wasm",
      "System.Console.x3b445tk8z.wasm": "System.Console.wasm",
      "System.Diagnostics.Debug.8e6oun3adh.wasm": "System.Diagnostics.Debug.wasm",
      "System.IO.Hashing.0axa7igz3n.wasm": "System.IO.Hashing.wasm",
      "System.IO.Pipelines.h6uh29vsor.wasm": "System.IO.Pipelines.wasm",
      "System.Linq.Expressions.dcu88kjcp5.wasm": "System.Linq.Expressions.wasm",
      "System.Linq.moxhw6mwjb.wasm": "System.Linq.wasm",
      "System.Memory.2gvwrzcdke.wasm": "System.Memory.wasm",
      "System.Net.Http.2gst3arw3t.wasm": "System.Net.Http.wasm",
      "System.Net.Primitives.tdq6frnmpt.wasm": "System.Net.Primitives.wasm",
      "System.ObjectModel.narjcl7hqk.wasm": "System.ObjectModel.wasm",
      "System.Private.CoreLib.sriltxfbbn.wasm": "System.Private.CoreLib.wasm",
      "System.Private.Uri.rjivi3py8t.wasm": "System.Private.Uri.wasm",
      "System.Resources.ResourceManager.bvxm0mvg3d.wasm": "System.Resources.ResourceManager.wasm",
      "System.Runtime.InteropServices.JavaScript.wowgk19gz9.wasm": "System.Runtime.InteropServices.JavaScript.wasm",
      "System.Runtime.f1c04imrdj.wasm": "System.Runtime.wasm",
      "System.Security.Cryptography.h633ixt19d.wasm": "System.Security.Cryptography.wasm",
      "System.Text.Encodings.Web.44k0ayxuht.wasm": "System.Text.Encodings.Web.wasm",
      "System.Text.Json.vmbx6t7089.wasm": "System.Text.Json.wasm",
      "System.Text.RegularExpressions.vzeqconkpp.wasm": "System.Text.RegularExpressions.wasm",
      "System.Threading.Tasks.9zoyzdg7ya.wasm": "System.Threading.Tasks.wasm",
      "System.ke1disal2r.wasm": "System.wasm",
      "theonlytool.lw4pau39bx.wasm": "theonlytool.wasm",
      "dotnet.js": "dotnet.js",
      "dotnet.native.6buk8i5pk6.wasm": "dotnet.native.wasm",
      "dotnet.native.xto5am0qhx.js": "dotnet.native.js",
      "dotnet.runtime.pu7sbjsy59.js": "dotnet.runtime.js",
      "icudt_CJK.tjcz0u77k5.dat": "icudt_CJK.dat",
      "icudt_EFIGS.tptq2av103.dat": "icudt_EFIGS.dat",
      "icudt_no_CJK.lfu7j35m59.dat": "icudt_no_CJK.dat"
    },
    "jsModuleNative": {
      "dotnet.native.xto5am0qhx.js": "sha256-9e5Vqt0u8nYMGCHU4JfYqrYQExAw3bgi5UYzATgvoJE="
    },
    "jsModuleRuntime": {
      "dotnet.runtime.pu7sbjsy59.js": "sha256-wW0L1H42TfMatybe1vKm/k57XP7qqXWX5r7AbCRx5JQ="
    },
    "wasmNative": {
      "dotnet.native.6buk8i5pk6.wasm": "sha256-jgmJHKTDZkqYH+tbs9FijgOzcdlK8XE/fg0FVI/ruU0="
    },
    "icu": {
      "icudt_CJK.tjcz0u77k5.dat": "sha256-SZLtQnRc0JkwqHab0VUVP7T3uBPSeYzxzDnpxPpUnHk=",
      "icudt_EFIGS.tptq2av103.dat": "sha256-8fItetYY8kQ0ww6oxwTLiT3oXlBwHKumbeP2pRF4yTc=",
      "icudt_no_CJK.lfu7j35m59.dat": "sha256-L7sV7NEYP37/Qr2FPCePo5cJqRgTXRwGHuwF5Q+0Nfs="
    },
    "coreAssembly": {
      "System.Private.CoreLib.sriltxfbbn.wasm": "sha256-uJx0CC4legvxMSumKmj3rb1WlBd5Yl2nGZsrtaEP15M=",
      "System.Runtime.InteropServices.JavaScript.wowgk19gz9.wasm": "sha256-gNHJDK7cciJTvbKVkr3kRqLROBhZNXjxk0K0F92k2cY="
    },
    "assembly": {
      "Microsoft.AspNetCore.Components.Forms.3qh9t4or2h.wasm": "sha256-BTHXkhy/9X3p+MX0/sm31OTLsBa/eASz8VZ7QmpdYzQ=",
      "Microsoft.AspNetCore.Components.Web.xxzncl2btm.wasm": "sha256-SwoMPlHS05yT2/LjqTYV4nO5fDMfNfd6qGFDDIKUa9U=",
      "Microsoft.AspNetCore.Components.WebAssembly.nvr1tj7rwf.wasm": "sha256-Y9y4a637WBoDa08GX7Qxx63oDFsCVE/4v8oZCvLkKTo=",
      "Microsoft.AspNetCore.Components.1jbluefeqp.wasm": "sha256-Y4zzyUUVBtaN6kfbmMJgFFFHhE50hCkIp86Snf6KGRs=",
      "Microsoft.Extensions.Configuration.Abstractions.s1desti5lj.wasm": "sha256-kMkTNci+rypvlVo91GsthRNT22k4Mk2BHQPk/Up3p7M=",
      "Microsoft.Extensions.Configuration.Json.6ap0l7oqnx.wasm": "sha256-/jB8J7byRl8++Sms23uw7dTZtf4OYQ+9wprtBqLHzvg=",
      "Microsoft.Extensions.Configuration.wzhhqnelnl.wasm": "sha256-XKu0mIlTddgbDgKXxAt72KH1jesOUPab12Fdli15Hmw=",
      "Microsoft.Extensions.DependencyInjection.t7f5r90yql.wasm": "sha256-t+RV090mInmcuQIlc498uXnF8wtK1MRNcmC72iNVUZI=",
      "Microsoft.Extensions.DependencyInjection.Abstractions.k3obqto650.wasm": "sha256-wDxLR6qY4LYrTg5jeBxNiFszgBwpRBTa+vd8DoBv5/E=",
      "Microsoft.Extensions.FileProviders.Abstractions.zo7f77cwpb.wasm": "sha256-s3caNLGikAlzK7Zbgsjf4RETQ43EcfRsHU3U76XDiz8=",
      "Microsoft.Extensions.Hosting.Abstractions.oq0bc6qwtw.wasm": "sha256-gNy3fBH1UFELrhJ7GxqLy+6tAxI1ca/R0lmCUqiJAkc=",
      "Microsoft.Extensions.Localization.Abstractions.ixsppbtym0.wasm": "sha256-tnMHqb6BpI1Jj9M9WNSAAJzzxHrQgov/aSXbFqc+xzk=",
      "Microsoft.Extensions.Localization.bvn14pws96.wasm": "sha256-6UgMJoVZBfDdfzYR0aKVK6BWArxpXC1qiQDDjiXw/L4=",
      "Microsoft.Extensions.Logging.bvp0h3knwz.wasm": "sha256-9x8FXDisdekP0Dbg8khNrE+Oocnngh9johtSRZyrZPk=",
      "Microsoft.Extensions.Logging.Abstractions.tx3rk9lhk3.wasm": "sha256-T8vdMKL2wM6XZ8W6A1SDa3vN5SWamebUijvh64HMJ0Q=",
      "Microsoft.Extensions.Options.7oidopj7m4.wasm": "sha256-OVRNJEKe9y6xOoqXrWmX+sOMl/uyQiSc5cYEYWMiUY0=",
      "Microsoft.Extensions.Primitives.a5mjza44y9.wasm": "sha256-Il7b7g4iQZWSTrBCdBft+EmS4u4r3VgzpqSIb4bfvTI=",
      "Microsoft.JSInterop.evnp8zttjq.wasm": "sha256-5jZf2QiBkRnLptGZ9aRYLks5RgacU3aWxXt53Xj8BUY=",
      "Microsoft.JSInterop.WebAssembly.9tiedlnvko.wasm": "sha256-vScvGCGFOzwoTsy7VKfMU9uuEskXbOdWabIc80iDa9g=",
      "MudBlazor.65z43161st.wasm": "sha256-6rETCV3S3KdEjilEkpXZqjRmygknG7aqxUpotK6U++0=",
      "Services.Base64.8b93i9ca7z.wasm": "sha256-5Kf122F95+Zig3aJ8kzYKYIrgUGFet1dLlfXayhS4Kk=",
      "Services.Hashing.e8mmxusnr1.wasm": "sha256-DpPJlkUGPNtvli6cKCwbCbhzfyJhDVrS+Z/J/DckKgU=",
      "Services.Url.ufhjhi9cut.wasm": "sha256-9leqJfM+ptKO2CW7gKlzgC0t2/vMpGAiJ++0EAdwA14=",
      "System.Collections.prf43m75vm.wasm": "sha256-Kywek6hKhB+x8qXklhR3hUyX4X5oMjJKNeqYhbo5N0k=",
      "System.Collections.Concurrent.ablm14sie8.wasm": "sha256-ZoZ4y0vzTk5FJAiTrEFQBOY0MwS+fU5Hd6VtofAh5B4=",
      "System.Collections.Immutable.s4jrvfcbhz.wasm": "sha256-ZMujjUhzn+72j9hYOdV8Umd64SnQAqh6VZkGvQMdelo=",
      "System.ComponentModel.Annotations.gruad1a9u6.wasm": "sha256-PGtsYnHAK0JIduyCVNcTWv6N/86AiQqMdMzD0PWt5LE=",
      "System.ComponentModel.Primitives.ai1jrkm3wb.wasm": "sha256-YnnIyAtyCiltvOTpTYJeGluEhUbSMMdePT4q2s6ewTg=",
      "System.ComponentModel.TypeConverter.p0djjcxzit.wasm": "sha256-V8TB7C9qw0DHB397CTHhPM1RC79uvI99MV+EW0550Oo=",
      "System.ComponentModel.fac0tpga5u.wasm": "sha256-yQDSFCIlXbqfv0DlqrFa4eUdlegHftxHiGmAVf5BRyk=",
      "System.Console.x3b445tk8z.wasm": "sha256-PZk070YbRPgSuTeVdKup7fLjoo2wlE3p2OPYx61TB4U=",
      "System.Diagnostics.Debug.8e6oun3adh.wasm": "sha256-oH/8K9Quvwr1xF/gHLSwAxm7MS7bipMU48lGELEqz40=",
      "System.IO.Hashing.0axa7igz3n.wasm": "sha256-CIqS8wFfljeeelEziuph4w+XxtekN8Zyazv2py/VP3w=",
      "System.IO.Pipelines.h6uh29vsor.wasm": "sha256-CanVWuvnie8m5xGa/F0a0AfsW5xhIL2sa6h8boZUlBw=",
      "System.Linq.Expressions.dcu88kjcp5.wasm": "sha256-Y6xxyghUecCGkQAs201im+zg17/1hIjttLif6u6mpDk=",
      "System.Linq.moxhw6mwjb.wasm": "sha256-xhyjI5dpqsIZL6FIdbJShnIloNcAM5mI+6c0/8YFfZE=",
      "System.Memory.2gvwrzcdke.wasm": "sha256-Ms75aDpJW/R/d4zEL3h4NwE920hhLc3jlrDGkGZNWS0=",
      "System.Net.Http.2gst3arw3t.wasm": "sha256-QjACl8ze+VN4GsnsWZYIv1CYlsiOtnCxIqbZjn1JqJs=",
      "System.Net.Primitives.tdq6frnmpt.wasm": "sha256-EXaV6eCut14fBZGU53+bsBz0eO67ykeCWVGoNpiS1BM=",
      "System.ObjectModel.narjcl7hqk.wasm": "sha256-78AmhAmA8r8W5HXMZHuVaKFQkjFwYuYKVVoVZQq0p7A=",
      "System.Private.Uri.rjivi3py8t.wasm": "sha256-WULz3fp6QsyT7xgho067edbdiTh9DTi2u0rSM1DpTSA=",
      "System.Resources.ResourceManager.bvxm0mvg3d.wasm": "sha256-91xIUxqJkw5si6G02MPGSyDzGSiWVmAlWhfm8sk5T7o=",
      "System.Runtime.f1c04imrdj.wasm": "sha256-82h72GmXArRhe02mRnfdg7MXZGE0j5tfT6ScNOmOUcA=",
      "System.Security.Cryptography.h633ixt19d.wasm": "sha256-2bgOMT9R4a5UQfEc4AjZrvDuNtKVl1iKpySa1oov+cw=",
      "System.Text.Encodings.Web.44k0ayxuht.wasm": "sha256-LPizL+reODGXix9Mv1USpe2aPbBzNkq1jJxkuC974b0=",
      "System.Text.Json.vmbx6t7089.wasm": "sha256-2XyEGYIJseDGQ5ua/aqNUHn/G6cGT1HWHnScSz7lTaE=",
      "System.Text.RegularExpressions.vzeqconkpp.wasm": "sha256-ldXVUEwA2j2+nbc9aNyRF+UpmXWlXimLD+PLn4IELDA=",
      "System.Threading.Tasks.9zoyzdg7ya.wasm": "sha256-Czbd+mdlakOcfHN4ibncHjcipTeJHTIHoVcr8Mkvle8=",
      "System.ke1disal2r.wasm": "sha256-pJVfOQBBtR7pVRj/hsDjW2tSJr3eMSs6yVHVGbiVf2s=",
      "theonlytool.lw4pau39bx.wasm": "sha256-6yiy5NrBc0LGJrBqElsLLiT445PbUgK6aCSBfxa0dDU="
    }
  },
  "cacheBootResources": true,
  "debugLevel": 0,
  "linkerEnabled": true,
  "globalizationMode": "sharded",
  "extensions": {
    "blazor": {}
  }
}